docvault/__init__.py
docvault/config.py
docvault/main.py
docvault/project.py
docvault/version.py
docvault/cli/__init__.py
docvault/cli/cache_commands.py
docvault/cli/collection_commands.py
docvault/cli/commands.py
docvault/cli/credential_commands.py
docvault/cli/freshness_commands.py
docvault/cli/llms_commands.py
docvault/cli/performance_commands.py
docvault/cli/quick_add_commands.py
docvault/cli/ref_commands.py
docvault/cli/registry_commands.py
docvault/cli/section_commands.py
docvault/cli/security_commands.py
docvault/cli/tag_commands.py
docvault/cli/version_commands.py
docvault/core/__init__.py
docvault/core/caching.py
docvault/core/context_extractor.py
docvault/core/depth_analyzer.py
docvault/core/doc_type_detector.py
docvault/core/embeddings.py
docvault/core/embeddings_optimized.py
docvault/core/exceptions.py
docvault/core/initialization.py
docvault/core/library_manager.py
docvault/core/llms_txt.py
docvault/core/performance.py
docvault/core/processor.py
docvault/core/scraper.py
docvault/core/scraper_optimized.py
docvault/core/section_navigator.py
docvault/core/section_splitter.py
docvault/core/storage.py
docvault/core/suggestion_engine.py
docvault/core/summarizer.py
docvault/core/extractors/__init__.py
docvault/core/extractors/base.py
docvault/core/extractors/generic.py
docvault/core/extractors/mkdocs.py
docvault/core/extractors/nextjs.py
docvault/core/extractors/openapi.py
docvault/core/extractors/sphinx.py
docvault/db/__init__.py
docvault/db/batch_operations.py
docvault/db/connection_pool.py
docvault/db/migrations.py
docvault/db/operations.py
docvault/db/operations_llms.py
docvault/db/performance_indexes.py
docvault/db/query_builder.py
docvault/db/schema.py
docvault/db/sql_logging.py
docvault/db/migrations/0001_add_section_fields.py
docvault/db/migrations/__init__.py
docvault/db/migrations/add_caching_fields_0006.py
docvault/db/migrations/add_collections_0007.py
docvault/db/migrations/add_content_extraction_fields_0006.py
docvault-0.7.0.dist-info/licenses/LICENSE
docvault-0.7.0.dist-info/METADATA
docvault-0.7.0.dist-info/WHEEL
docvault-0.7.0.dist-info/entry_points.txt
docvault-0.7.0.dist-info/top_level.txt
docvault-0.7.0.dist-info/RECORD
