Metadata-Version: 2.4
Name: docvault
Version: 0.7.0
Summary: Document fetching and management system with vector search and MCP integration
Author-email: Hysun Chung <hysun@hysun.com>
License-Expression: MIT
Requires-Python: >=3.12
License-File: LICENSE
Requires-Dist: click>=8.1.3
Requires-Dist: rich>=13.3.1
Requires-Dist: python-dotenv>=1.0.0
Requires-Dist: requests>=2.28.1
Requires-Dist: beautifulsoup4>=4.11.1
Requires-Dist: html2text>=2020.1.16
Requires-Dist: aiohttp>=3.8.4
Requires-Dist: numpy>=1.24.0
Requires-Dist: markdown-it-py>=2.2.0
Requires-Dist: httpx>=0.23.3
Requires-Dist: httpx-sse>=0.3.0
Requires-Dist: mcp[cli]>=1.3.0
Requires-Dist: sqlite-vec>=0.1.6
Requires-Dist: toml>=0.10.2
Requires-Dist: cryptography>=41.0.0
Provides-Extra: dev
Requires-Dist: pytest>=7.0.0; extra == "dev"
Requires-Dist: pytest-asyncio>=0.20.0; extra == "dev"
Requires-Dist: pytest-cov>=4.0.0; extra == "dev"
Requires-Dist: click>=8.1.3; extra == "dev"
Requires-Dist: rich>=13.3.1; extra == "dev"
Dynamic: license-file
